twittenizer/__init__.py
twittenizer/__main__.py
twittenizer/nltk_tweet_tokenizer.py
twittenizer/tokenizer.py
twittenizer-0.0.5.dist-info/LICENSE
twittenizer-0.0.5.dist-info/METADATA
twittenizer-0.0.5.dist-info/WHEEL
twittenizer-0.0.5.dist-info/top_level.txt
twittenizer-0.0.5.dist-info/RECORD
