Metadata-Version: 2.1
Name: twittenizer
Version: 0.0.5
Summary: UNKNOWN
Home-page: https://github.com/Kydlaw/twittenizer
Author: Kydlaw
Author-email: kydlawj@pm.me
License: UNKNOWN
Keywords: tokenizer twitter
Platform: UNKNOWN
Requires-Python: >=3.5
Requires-Dist: regex
Requires-Dist: pymongo
